taskframe/__init__.py
taskframe/client.py
taskframe/dataset.py
taskframe/task.py
taskframe/taskframe.py
taskframe/team_member.py
taskframe/utils.py
taskframe-0.1.13.dist-info/LICENSE
taskframe-0.1.13.dist-info/METADATA
taskframe-0.1.13.dist-info/WHEEL
taskframe-0.1.13.dist-info/top_level.txt
taskframe-0.1.13.dist-info/RECORD
