Metadata-Version: 2.1
Name: taskframe
Version: 0.1.13
Summary: Taskframe Python client
Home-page: https://github.com/Taskframe/taskframe-python
Author: Denis Vilar
License: UNKNOWN
Platform: UNKNOWN
Classifier: Programming Language :: Python :: 3
Classifier: License :: OSI Approved :: MIT License
Classifier: Operating System :: OS Independent
Requires-Python: >=3.6
Requires-Dist: ipython (>=5.5.0)
Requires-Dist: requests (>=2.4.2)
